LICENSE.txt
MANIFEST.in
README.rst
setup.cfg
setup.py
test-requirements.txt
laa/__init__.py
laa/laa.py
laa.egg-info/PKG-INFO
laa.egg-info/SOURCES.txt
laa.egg-info/dependency_links.txt
laa.egg-info/top_level.txt