Metadata-Version: 1.1
Name: laa
Version: 0.1.3
Summary: Lazy Replacements for »any« and »all« with lambdas
Home-page: https://github.com/edelbluth/laa
Author: Juergen Edelbluth
Author-email: dev@juergen.rocks
License: Apache License 2.0
Download-URL: https://github.com/edelbluth/laa/tarball/v0.1.3
Keywords: any,all,lazy,short circuit,sce,short circuit evaluation,lambda
Platform: UNKNOWN
Classifier: Development Status :: 4 - Beta
Classifier: Intended Audience :: Developers
Classifier: License :: OSI Approved :: Apache Software License
Classifier: Operating System :: OS Independent
Classifier: Programming Language :: Python :: 3 :: Only
Classifier: Topic :: Software Development :: Libraries :: Python Modules
